{
  "daily": [
    {
      "date": "2025-10-20",
      "matches": [
        {
          "date": "2025-10-20",
          "league": "Eredivisie",
          "match": "Telstar vs Heerenveen",
          "fixture_id": 1380946,
          "projected_score": "2.18 - 1.56",
          "actual_score": "2 - 3",
          "avg_diff": 0.81,
          "accuracy_score": 79.8
        },
        {
          "date": "2025-10-20",
          "league": "Serie A",
          "match": "Como vs Juventus",
          "fixture_id": 1377926,
          "projected_score": "1.29 - 1.20",
          "actual_score": "2 - 0",
          "avg_diff": 0.95,
          "accuracy_score": 76.2
        },
        {
          "date": "2025-10-20",
          "league": "La Liga",
          "match": "Elche vs Athletic Club",
          "fixture_id": 1390903,
          "projected_score": "1.32 - 0.95",
          "actual_score": "0 - 0",
          "avg_diff": 1.14,
          "accuracy_score": 71.5
        },
        {
          "date": "2025-10-20",
          "league": "Eredivisie",
          "match": "Groningen vs Sparta",
          "fixture_id": 1380944,
          "projected_score": "1.58 - 1.27",
          "actual_score": "0 - 2",
          "avg_diff": 1.16,
          "accuracy_score": 71.0
        },
        {
          "date": "2025-10-20",
          "league": "Eredivisie",
          "match": "Excelsior vs Fortuna Sittard",
          "fixture_id": 1380945,
          "projected_score": "1.70 - 1.19",
          "actual_score": "1 - 0",
          "avg_diff": 0.94,
          "accuracy_score": 76.5
        },
        {
          "date": "2025-10-20",
          "league": "Serie A",
          "match": "Cagliari vs Bologna",
          "fixture_id": 1377925,
          "projected_score": "1.43 - 1.06",
          "actual_score": "0 - 2",
          "avg_diff": 1.19,
          "accuracy_score": 70.2
        },
        {
          "date": "2025-10-20",
          "league": "Serie A",
          "match": "Genoa vs Parma",
          "fixture_id": 1377928,
          "projected_score": "1.31 - 1.51",
          "actual_score": "0 - 0",
          "avg_diff": 1.41,
          "accuracy_score": 64.8
        },
        {
          "date": "2025-10-20",
          "league": "Premier League",
          "match": "Tottenham vs Aston Villa",
          "fixture_id": 1379047,
          "projected_score": "1.61 - 1.25",
          "actual_score": "1 - 2",
          "avg_diff": 0.68,
          "accuracy_score": 83.0
        },
        {
          "date": "2025-10-20",
          "league": "Ligue 1",
          "match": "Lens vs Paris FC",
          "fixture_id": 1387762,
          "projected_score": "1.41 - 0.88",
          "actual_score": "2 - 1",
          "avg_diff": 0.36,
          "accuracy_score": 91.0
        },
        {
          "date": "2025-10-20",
          "league": "Bundesliga",
          "match": "Freiburg vs Frankfurt",
          "fixture_id": 1388364,
          "projected_score": "1.80 - 2.11",
          "actual_score": "2 - 2",
          "avg_diff": 0.15,
          "accuracy_score": 96.2
        },
        {
          "date": "2025-10-20",
          "league": "La Liga",
          "match": "Celta Vigo vs Real Sociedad",
          "fixture_id": 1390902,
          "projected_score": "1.31 - 1.16",
          "actual_score": "1 - 1",
          "avg_diff": 0.23,
          "accuracy_score": 94.2
        },
        {
          "date": "2025-10-20",
          "league": "Eredivisie",
          "match": "Heracles vs Feyenoord",
          "fixture_id": 1380939,
          "projected_score": "1.28 - 2.68",
          "actual_score": "0 - 7",
          "avg_diff": 2.8,
          "accuracy_score": 30.0
        },
        {
          "date": "2025-10-20",
          "league": "Ligue 1",
          "match": "Lorient vs Stade Brestois 29",
          "fixture_id": 1387763,
          "projected_score": "1.91 - 1.63",
          "actual_score": "3 - 3",
          "avg_diff": 1.23,
          "accuracy_score": 69.2
        },
        {
          "date": "2025-10-20",
          "league": "Ligue 1",
          "match": "Rennes vs Auxerre",
          "fixture_id": 1387768,
          "projected_score": "1.78 - 0.66",
          "actual_score": "2 - 2",
          "avg_diff": 0.78,
          "accuracy_score": 80.5
        },
        {
          "date": "2025-10-20",
          "league": "Ligue 1",
          "match": "Toulouse vs Metz",
          "fixture_id": 1387769,
          "projected_score": "2.50 - 1.34",
          "actual_score": "4 - 0",
          "avg_diff": 1.42,
          "accuracy_score": 64.5
        },
        {
          "date": "2025-10-20",
          "league": "Premier League",
          "match": "Liverpool vs Man United",
          "fixture_id": 1379043,
          "projected_score": "2.78 - 0.71",
          "actual_score": "1 - 2",
          "avg_diff": 1.53,
          "accuracy_score": 61.8
        },
        {
          "date": "2025-10-20",
          "league": "Bundesliga",
          "match": "St. Pauli vs Hoffenheim",
          "fixture_id": 1388368,
          "projected_score": "1.45 - 1.42",
          "actual_score": "0 - 3",
          "avg_diff": 1.52,
          "accuracy_score": 62.0
        },
        {
          "date": "2025-10-20",
          "league": "Serie A",
          "match": "Atalanta vs Lazio",
          "fixture_id": 1377924,
          "projected_score": "1.67 - 1.45",
          "actual_score": "0 - 0",
          "avg_diff": 1.56,
          "accuracy_score": 61.0
        },
        {
          "date": "2025-10-20",
          "league": "La Liga",
          "match": "Levante vs Rayo Vallecano",
          "fixture_id": 1390905,
          "projected_score": "1.66 - 1.59",
          "actual_score": "0 - 3",
          "avg_diff": 1.53,
          "accuracy_score": 61.8
        },
        {
          "date": "2025-10-20",
          "league": "Serie A",
          "match": "AC Milan vs Fiorentina",
          "fixture_id": 1377930,
          "projected_score": "1.46 - 0.81",
          "actual_score": "2 - 1",
          "avg_diff": 0.36,
          "accuracy_score": 91.0
        },
        {
          "date": "2025-10-20",
          "league": "Ligue 1",
          "match": "Nantes vs Lille",
          "fixture_id": 1387765,
          "projected_score": "1.21 - 1.48",
          "actual_score": "0 - 2",
          "avg_diff": 0.86,
          "accuracy_score": 78.5
        },
        {
          "date": "2025-10-20",
          "league": "La Liga",
          "match": "Getafe vs Real Madrid",
          "fixture_id": 1390904,
          "projected_score": "0.79 - 1.46",
          "actual_score": "0 - 1",
          "avg_diff": 0.62,
          "accuracy_score": 84.5
        }
      ]
    },
    {
      "date": "2025-10-20",
      "matches": [
        {
          "date": "2025-10-20",
          "league": "Serie A",
          "match": "Cremonese vs Udinese",
          "fixture_id": 1377927,
          "projected_score": "1.45 - 1.17",
          "actual_score": "1 - 1",
          "avg_diff": 0.31,
          "accuracy_score": 92.2
        },
        {
          "date": "2025-10-20",
          "league": "Premier League",
          "match": "West Ham vs Brentford",
          "fixture_id": 1379048,
          "projected_score": "1.52 - 1.80",
          "actual_score": "0 - 2",
          "avg_diff": 0.86,
          "accuracy_score": 78.5
        },
        {
          "date": "2025-10-20",
          "league": "La Liga",
          "match": "Alaves vs Valencia",
          "fixture_id": 1390899,
          "projected_score": "1.81 - 0.87",
          "actual_score": "0 - 0",
          "avg_diff": 1.34,
          "accuracy_score": 66.5
        }
      ]
    },
    {
      "date": "2025-10-21",
      "matches": [
        {
          "date": "2025-10-21",
          "league": "UEFA Champions League",
          "match": "Kairat Almaty vs Pafos",
          "fixture_id": 1451056,
          "projected_score": "1.46 - 1.63",
          "actual_score": "0 - 0",
          "avg_diff": 1.54,
          "accuracy_score": 61.5
        },
        {
          "date": "2025-10-21",
          "league": "UEFA Champions League",
          "match": "Barcelona vs Olympiakos",
          "fixture_id": 1451057,
          "projected_score": "4.07 - 0.61",
          "actual_score": "6 - 1",
          "avg_diff": 1.16,
          "accuracy_score": 71.0
        },
        {
          "date": "2025-10-21",
          "league": "UEFA Champions League",
          "match": "USG vs Inter",
          "fixture_id": 1451058,
          "projected_score": "1.59 - 1.53",
          "actual_score": "0 - 4",
          "avg_diff": 2.03,
          "accuracy_score": 49.3
        },
        {
          "date": "2025-10-21",
          "league": "UEFA Champions League",
          "match": "PSV vs Napoli",
          "fixture_id": 1451059,
          "projected_score": "1.56 - 1.89",
          "actual_score": "6 - 2",
          "avg_diff": 2.27,
          "accuracy_score": 43.2
        },
        {
          "date": "2025-10-21",
          "league": "UEFA Champions League",
          "match": "Leverkusen vs PSG",
          "fixture_id": 1451060,
          "projected_score": "1.23 - 2.47",
          "actual_score": "2 - 7",
          "avg_diff": 2.65,
          "accuracy_score": 33.8
        },
        {
          "date": "2025-10-21",
          "league": "UEFA Champions League",
          "match": "Arsenal vs Atletico",
          "fixture_id": 1451061,
          "projected_score": "2.20 - 0.75",
          "actual_score": "4 - 0",
          "avg_diff": 1.27,
          "accuracy_score": 68.2
        },
        {
          "date": "2025-10-21",
          "league": "UEFA Champions League",
          "match": "Copenhagen vs Dortmund",
          "fixture_id": 1451062,
          "projected_score": "1.28 - 2.16",
          "actual_score": "2 - 4",
          "avg_diff": 1.28,
          "accuracy_score": 68.0
        },
        {
          "date": "2025-10-21",
          "league": "UEFA Champions League",
          "match": "Villarreal vs Man City",
          "fixture_id": 1451063,
          "projected_score": "1.40 - 1.75",
          "actual_score": "0 - 2",
          "avg_diff": 0.82,
          "accuracy_score": 79.5
        },
        {
          "date": "2025-10-21",
          "league": "UEFA Champions League",
          "match": "Newcastle vs Benfica",
          "fixture_id": 1451064,
          "projected_score": "1.85 - 1.12",
          "actual_score": "3 - 0",
          "avg_diff": 1.14,
          "accuracy_score": 71.5
        }
      ]
    },
    {
      "date": "2025-10-22",
      "matches": [
        {
          "date": "2025-10-22",
          "league": "UEFA Champions League",
          "match": "Galatasaray vs Bodo/Glimt",
          "fixture_id": 1451065,
          "projected_score": "2.16 - 1.35",
          "actual_score": "3 - 1",
          "avg_diff": 0.59,
          "accuracy_score": 85.2
        },
        {
          "date": "2025-10-22",
          "league": "UEFA Champions League",
          "match": "Athletic Club vs Qarabag",
          "fixture_id": 1451066,
          "projected_score": "2.15 - 0.97",
          "actual_score": "3 - 1",
          "avg_diff": 0.44,
          "accuracy_score": 89.0
        },
        {
          "date": "2025-10-22",
          "league": "UEFA Champions League",
          "match": "Monaco vs Tottenham",
          "fixture_id": 1451067,
          "projected_score": "1.73 - 1.79",
          "actual_score": "0 - 0",
          "avg_diff": 1.76,
          "accuracy_score": 56.0
        },
        {
          "date": "2025-10-22",
          "league": "UEFA Champions League",
          "match": "Real Madrid vs Juventus",
          "fixture_id": 1451068,
          "projected_score": "1.99 - 0.84",
          "actual_score": "1 - 0",
          "avg_diff": 0.92,
          "accuracy_score": 77.0
        },
        {
          "date": "2025-10-22",
          "league": "UEFA Champions League",
          "match": "Frankfurt vs Liverpool",
          "fixture_id": 1451069,
          "projected_score": "1.70 - 2.42",
          "actual_score": "1 - 5",
          "avg_diff": 1.64,
          "accuracy_score": 59.0
        },
        {
          "date": "2025-10-22",
          "league": "UEFA Champions League",
          "match": "Chelsea vs Ajax",
          "fixture_id": 1451070,
          "projected_score": "3.04 - 1.11",
          "actual_score": "5 - 1",
          "avg_diff": 1.04,
          "accuracy_score": 74.0
        },
        {
          "date": "2025-10-22",
          "league": "UEFA Champions League",
          "match": "Atalanta vs Slavia",
          "fixture_id": 1451071,
          "projected_score": "2.58 - 0.85",
          "actual_score": "0 - 0",
          "avg_diff": 1.72,
          "accuracy_score": 57.0
        },
        {
          "date": "2025-10-22",
          "league": "UEFA Champions League",
          "match": "Sporting vs Marseille",
          "fixture_id": 1451072,
          "projected_score": "1.80 - 1.28",
          "actual_score": "2 - 1",
          "avg_diff": 0.24,
          "accuracy_score": 94.0
        },
        {
          "date": "2025-10-22",
          "league": "UEFA Champions League",
          "match": "Bayern vs Brugge",
          "fixture_id": 1451073,
          "projected_score": "4.16 - 0.64",
          "actual_score": "4 - 0",
          "avg_diff": 0.4,
          "accuracy_score": 90.0
        }
      ]
    },
    {
      "date": "2025-10-23",
      "matches": [
        {
          "date": "2025-10-23",
          "league": "UEFA Europa League",
          "match": "Fenerbahce vs Stuttgart",
          "fixture_id": 1451197,
          "projected_score": "1.38 - 1.93",
          "actual_score": "1 - 0",
          "avg_diff": 1.15,
          "accuracy_score": 71.2
        },
        {
          "date": "2025-10-23",
          "league": "UEFA Europa League",
          "match": "Brann vs Rangers",
          "fixture_id": 1451198,
          "projected_score": "1.84 - 1.33",
          "actual_score": "3 - 0",
          "avg_diff": 1.25,
          "accuracy_score": 68.8
        },
        {
          "date": "2025-10-23",
          "league": "UEFA Europa League",
          "match": "GO Ahead vs Aston Villa",
          "fixture_id": 1451199,
          "projected_score": "1.05 - 1.83",
          "actual_score": "2 - 1",
          "avg_diff": 0.89,
          "accuracy_score": 77.8
        },
        {
          "date": "2025-10-23",
          "league": "UEFA Europa League",
          "match": "Genk vs Real Betis",
          "fixture_id": 1451200,
          "projected_score": "1.25 - 1.82",
          "actual_score": "0 - 0",
          "avg_diff": 1.54,
          "accuracy_score": 61.5
        },
        {
          "date": "2025-10-23",
          "league": "UEFA Europa League",
          "match": "Feyenoord vs Panathinaikos",
          "fixture_id": 1451201,
          "projected_score": "2.95 - 0.88",
          "actual_score": "3 - 1",
          "avg_diff": 0.08,
          "accuracy_score": 98.0
        },
        {
          "date": "2025-10-23",
          "league": "UEFA Europa League",
          "match": "RB Salzburg vs Ferencvarosi",
          "fixture_id": 1451202,
          "projected_score": "2.18 - 1.27",
          "actual_score": "2 - 3",
          "avg_diff": 0.96,
          "accuracy_score": 76.0
        },
        {
          "date": "2025-10-23",
          "league": "UEFA Europa League",
          "match": "Lyon vs FC Basel",
          "fixture_id": 1451203,
          "projected_score": "3.07 - 0.84",
          "actual_score": "2 - 0",
          "avg_diff": 0.95,
          "accuracy_score": 76.2
        },
        {
          "date": "2025-10-23",
          "league": "UEFA Europa League",
          "match": "Braga vs Crvena Zvezda",
          "fixture_id": 1451204,
          "projected_score": "2.29 - 1.27",
          "actual_score": "2 - 0",
          "avg_diff": 0.78,
          "accuracy_score": 80.5
        },
        {
          "date": "2025-10-23",
          "league": "UEFA Europa League",
          "match": "FCSB vs Bologna",
          "fixture_id": 1451205,
          "projected_score": "0.59 - 2.45",
          "actual_score": "1 - 2",
          "avg_diff": 0.43,
          "accuracy_score": 89.2
        },
        {
          "date": "2025-10-23",
          "league": "UEFA Europa League",
          "match": "Celta Vigo vs Nice",
          "fixture_id": 1451206,
          "projected_score": "2.18 - 1.22",
          "actual_score": "2 - 1",
          "avg_diff": 0.2,
          "accuracy_score": 95.0
        },
        {
          "date": "2025-10-23",
          "league": "UEFA Europa League",
          "match": "Young Boys vs Ludogorets",
          "fixture_id": 1451207,
          "projected_score": "1.92 - 1.04",
          "actual_score": "3 - 2",
          "avg_diff": 1.02,
          "accuracy_score": 74.5
        },
        {
          "date": "2025-10-23",
          "league": "UEFA Europa League",
          "match": "Celtic vs Sturm Graz",
          "fixture_id": 1451208,
          "projected_score": "2.09 - 1.04",
          "actual_score": "2 - 1",
          "avg_diff": 0.06,
          "accuracy_score": 98.5
        },
        {
          "date": "2025-10-23",
          "league": "UEFA Europa League",
          "match": "AS Roma vs Plzen",
          "fixture_id": 1451209,
          "projected_score": "2.77 - 0.72",
          "actual_score": "1 - 2",
          "avg_diff": 1.52,
          "accuracy_score": 62.0
        },
        {
          "date": "2025-10-23",
          "league": "UEFA Europa League",
          "match": "Nottingham Forest vs FC Porto",
          "fixture_id": 1451210,
          "projected_score": "1.33 - 1.48",
          "actual_score": "2 - 0",
          "avg_diff": 1.07,
          "accuracy_score": 73.2
        },
        {
          "date": "2025-10-23",
          "league": "UEFA Europa League",
          "match": "Maccabi vs Midtjylland",
          "fixture_id": 1451211,
          "projected_score": "1.25 - 1.48",
          "actual_score": "0 - 3",
          "avg_diff": 1.39,
          "accuracy_score": 65.2
        },
        {
          "date": "2025-10-23",
          "league": "UEFA Europa League",
          "match": "Lille vs PAOK",
          "fixture_id": 1451212,
          "projected_score": "2.78 - 1.02",
          "actual_score": "3 - 4",
          "avg_diff": 1.6,
          "accuracy_score": 60.0
        },
        {
          "date": "2025-10-23",
          "league": "UEFA Europa League",
          "match": "Malmo FF vs Dinamo Zagreb",
          "fixture_id": 1451213,
          "projected_score": "1.43 - 1.36",
          "actual_score": "1 - 1",
          "avg_diff": 0.4,
          "accuracy_score": 90.0
        },
        {
          "date": "2025-10-23",
          "league": "UEFA Europa League",
          "match": "SC Freiburg vs Utrecht",
          "fixture_id": 1452156,
          "projected_score": "2.43 - 1.24",
          "actual_score": "2 - 0",
          "avg_diff": 0.84,
          "accuracy_score": 79.0
        }
      ]
    },
    {
      "date": "2025-10-24",
      "matches": [
        {
          "date": "2025-10-24",
          "league": "Eredivisie",
          "match": "Heerenveen vs NAC Breda",
          "fixture_id": 1380948,
          "projected_score": "2.04 - 0.72",
          "actual_score": "3 - 3",
          "avg_diff": 1.62,
          "accuracy_score": 59.5
        },
        {
          "date": "2025-10-24",
          "league": "Bundesliga",
          "match": "Werder Bremen vs Union Berlin",
          "fixture_id": 1388379,
          "projected_score": "1.80 - 1.50",
          "actual_score": "1 - 0",
          "avg_diff": 1.15,
          "accuracy_score": 71.2
        },
        {
          "date": "2025-10-24",
          "league": "Serie A",
          "match": "AC Milan vs Pisa",
          "fixture_id": 1377937,
          "projected_score": "2.27 - 0.98",
          "actual_score": "2 - 2",
          "avg_diff": 0.65,
          "accuracy_score": 83.8
        },
        {
          "date": "2025-10-24",
          "league": "Ligue 1",
          "match": "Paris FC vs Nantes",
          "fixture_id": 1387777,
          "projected_score": "2.12 - 1.22",
          "actual_score": "1 - 2",
          "avg_diff": 0.95,
          "accuracy_score": 76.2
        },
        {
          "date": "2025-10-24",
          "league": "Premier League",
          "match": "Leeds vs West Ham",
          "fixture_id": 1379055,
          "projected_score": "1.40 - 1.33",
          "actual_score": "2 - 1",
          "avg_diff": 0.47,
          "accuracy_score": 88.2
        },
        {
          "date": "2025-10-24",
          "league": "La Liga",
          "match": "Real Sociedad vs Sevilla",
          "fixture_id": 1390917,
          "projected_score": "1.25 - 1.22",
          "actual_score": "2 - 1",
          "avg_diff": 0.48,
          "accuracy_score": 88.0
        }
      ]
    },
    {
      "date": "2025-10-25",
      "matches": [
        {
          "date": "2025-10-25",
          "league": "La Liga",
          "match": "Girona vs Oviedo",
          "fixture_id": 1390912,
          "projected_score": "1.28 - 0.90",
          "actual_score": "3 - 3",
          "avg_diff": 1.91,
          "accuracy_score": 52.2
        },
        {
          "date": "2025-10-25",
          "league": "Serie A",
          "match": "Parma vs Como",
          "fixture_id": 1377939,
          "projected_score": "1.55 - 1.17",
          "actual_score": "0 - 0",
          "avg_diff": 1.36,
          "accuracy_score": 66.0
        },
        {
          "date": "2025-10-25",
          "league": "Serie A",
          "match": "Udinese vs Lecce",
          "fixture_id": 1377942,
          "projected_score": "1.31 - 0.99",
          "actual_score": "3 - 2",
          "avg_diff": 1.35,
          "accuracy_score": 66.2
        },
        {
          "date": "2025-10-25",
          "league": "Bundesliga",
          "match": "Augsburg vs RB Leipzig",
          "fixture_id": 1388371,
          "projected_score": "1.61 - 1.60",
          "actual_score": "0 - 6",
          "avg_diff": 3.01,
          "accuracy_score": 24.8
        },
        {
          "date": "2025-10-25",
          "league": "Bundesliga",
          "match": "Borussia M. vs Bayern",
          "fixture_id": 1388373,
          "projected_score": "1.21 - 3.46",
          "actual_score": "0 - 3",
          "avg_diff": 0.83,
          "accuracy_score": 79.2
        },
        {
          "date": "2025-10-25",
          "league": "Bundesliga",
          "match": "Frankfurt vs St. Pauli",
          "fixture_id": 1388375,
          "projected_score": "1.90 - 1.42",
          "actual_score": "2 - 0",
          "avg_diff": 0.76,
          "accuracy_score": 81.0
        },
        {
          "date": "2025-10-25",
          "league": "Bundesliga",
          "match": "Hamburger vs Wolfsburg",
          "fixture_id": 1388376,
          "projected_score": "1.46 - 1.30",
          "actual_score": "0 - 1",
          "avg_diff": 0.88,
          "accuracy_score": 78.0
        },
        {
          "date": "2025-10-25",
          "league": "Bundesliga",
          "match": "Hoffenheim vs Heidenheim",
          "fixture_id": 1388377,
          "projected_score": "1.52 - 1.34",
          "actual_score": "3 - 1",
          "avg_diff": 0.91,
          "accuracy_score": 77.2
        },
        {
          "date": "2025-10-25",
          "league": "Premier League",
          "match": "Chelsea vs Sunderland",
          "fixture_id": 1379053,
          "projected_score": "2.02 - 0.85",
          "actual_score": "1 - 2",
          "avg_diff": 1.08,
          "accuracy_score": 73.0
        },
        {
          "date": "2025-10-25",
          "league": "Premier League",
          "match": "Newcastle vs Fulham",
          "fixture_id": 1379057,
          "projected_score": "1.84 - 0.97",
          "actual_score": "2 - 1",
          "avg_diff": 0.09,
          "accuracy_score": 97.8
        },
        {
          "date": "2025-10-25",
          "league": "La Liga",
          "match": "Espanyol vs Elche",
          "fixture_id": 1390911,
          "projected_score": "1.87 - 1.23",
          "actual_score": "1 - 0",
          "avg_diff": 1.05,
          "accuracy_score": 73.8
        },
        {
          "date": "2025-10-25",
          "league": "Eredivisie",
          "match": "Fortuna Sittard vs Groningen",
          "fixture_id": 1380949,
          "projected_score": "1.87 - 1.51",
          "actual_score": "1 - 2",
          "avg_diff": 0.68,
          "accuracy_score": 83.0
        },
        {
          "date": "2025-10-25",
          "league": "Ligue 1",
          "match": "Brest vs PSG",
          "fixture_id": 1387772,
          "projected_score": "1.29 - 2.86",
          "actual_score": "0 - 3",
          "avg_diff": 0.72,
          "accuracy_score": 82.0
        },
        {
          "date": "2025-10-25",
          "league": "Serie A",
          "match": "Napoli vs Inter",
          "fixture_id": 1377938,
          "projected_score": "1.35 - 1.48",
          "actual_score": "3 - 1",
          "avg_diff": 1.06,
          "accuracy_score": 73.5
        },
        {
          "date": "2025-10-25",
          "league": "Premier League",
          "match": "Man United vs Brighton",
          "fixture_id": 1379056,
          "projected_score": "1.64 - 1.53",
          "actual_score": "4 - 2",
          "avg_diff": 1.42,
          "accuracy_score": 64.5
        },
        {
          "date": "2025-10-25",
          "league": "Bundesliga",
          "match": "Dortmund vs FC K\u00f6ln",
          "fixture_id": 1388374,
          "projected_score": "2.41 - 0.96",
          "actual_score": "1 - 0",
          "avg_diff": 1.19,
          "accuracy_score": 70.2
        },
        {
          "date": "2025-10-25",
          "league": "La Liga",
          "match": "Athletic Club vs Getafe",
          "fixture_id": 1390909,
          "projected_score": "1.77 - 0.96",
          "actual_score": "0 - 1",
          "avg_diff": 0.91,
          "accuracy_score": 77.2
        },
        {
          "date": "2025-10-25",
          "league": "Eredivisie",
          "match": "Sparta Rotterdam vs Telstar",
          "fixture_id": 1380951,
          "projected_score": "1.83 - 1.66",
          "actual_score": "1 - 0",
          "avg_diff": 1.25,
          "accuracy_score": 68.8
        },
        {
          "date": "2025-10-25",
          "league": "Ligue 1",
          "match": "Monaco vs Toulouse",
          "fixture_id": 1387776,
          "projected_score": "1.93 - 1.28",
          "actual_score": "1 - 0",
          "avg_diff": 1.1,
          "accuracy_score": 72.5
        },
        {
          "date": "2025-10-25",
          "league": "Eredivisie",
          "match": "Volendam vs Heracles",
          "fixture_id": 1380950,
          "projected_score": "2.20 - 1.14",
          "actual_score": "3 - 0",
          "avg_diff": 0.97,
          "accuracy_score": 75.8
        },
        {
          "date": "2025-10-25",
          "league": "Serie A",
          "match": "Cremonese vs Atalanta",
          "fixture_id": 1377934,
          "projected_score": "1.31 - 1.64",
          "actual_score": "1 - 1",
          "avg_diff": 0.47,
          "accuracy_score": 88.2
        },
        {
          "date": "2025-10-25",
          "league": "Premier League",
          "match": "Brentford vs Liverpool",
          "fixture_id": 1379052,
          "projected_score": "1.75 - 2.00",
          "actual_score": "3 - 2",
          "avg_diff": 0.62,
          "accuracy_score": 84.5
        },
        {
          "date": "2025-10-25",
          "league": "Eredivisie",
          "match": "PEC Zwolle vs NEC",
          "fixture_id": 1380952,
          "projected_score": "1.38 - 1.42",
          "actual_score": "2 - 2",
          "avg_diff": 0.6,
          "accuracy_score": 85.0
        },
        {
          "date": "2025-10-25",
          "league": "La Liga",
          "match": "Valencia vs Villarreal",
          "fixture_id": 1390918,
          "projected_score": "1.90 - 1.01",
          "actual_score": "0 - 2",
          "avg_diff": 1.44,
          "accuracy_score": 64.0
        },
        {
          "date": "2025-10-25",
          "league": "Ligue 1",
          "match": "Lens vs Marseille",
          "fixture_id": 1387773,
          "projected_score": "1.43 - 1.39",
          "actual_score": "2 - 1",
          "avg_diff": 0.48,
          "accuracy_score": 88.0
        }
      ]
    }
  ],
  "leagues": [
    {
      "league": "Eredivisie",
      "games_tracked": 9,
      "dg_score": 69.9,
      "sim_avg_goals": 3.25,
      "actual_avg_goals": 3.56,
      "actual_btts_pct": 44.4,
      "actual_over25_pct": 66.7
    },
    {
      "league": "Serie A",
      "games_tracked": 11,
      "dg_score": 75.7,
      "sim_avg_goals": 2.71,
      "actual_avg_goals": 2.18,
      "actual_btts_pct": 54.5,
      "actual_over25_pct": 36.4
    },
    {
      "league": "La Liga",
      "games_tracked": 10,
      "dg_score": 73.4,
      "sim_avg_goals": 2.63,
      "actual_avg_goals": 1.9,
      "actual_btts_pct": 30.0,
      "actual_over25_pct": 30.0
    },
    {
      "league": "Premier League",
      "games_tracked": 8,
      "dg_score": 78.9,
      "sim_avg_goals": 3.12,
      "actual_avg_goals": 3.5,
      "actual_btts_pct": 87.5,
      "actual_over25_pct": 87.5
    },
    {
      "league": "Ligue 1",
      "games_tracked": 9,
      "dg_score": 78.0,
      "sim_avg_goals": 3.15,
      "actual_avg_goals": 3.22,
      "actual_btts_pct": 55.6,
      "actual_over25_pct": 77.8
    },
    {
      "league": "Bundesliga",
      "games_tracked": 9,
      "dg_score": 71.1,
      "sim_avg_goals": 3.36,
      "actual_avg_goals": 2.78,
      "actual_btts_pct": 22.2,
      "actual_over25_pct": 55.6
    },
    {
      "league": "UEFA Champions League",
      "games_tracked": 18,
      "dg_score": 68.2,
      "sim_avg_goals": 3.51,
      "actual_avg_goals": 3.94,
      "actual_btts_pct": 50.0,
      "actual_over25_pct": 72.2
    },
    {
      "league": "UEFA Europa League",
      "games_tracked": 18,
      "dg_score": 77.6,
      "sim_avg_goals": 3.28,
      "actual_avg_goals": 2.94,
      "actual_btts_pct": 55.6,
      "actual_over25_pct": 61.1
    }
  ]
}