[
  {
    "id": 19124,
    "team_id": 375,
    "name": "P. Jansson",
    "position": "Defender",
    "appearances": 10,
    "minutes": 930,
    "goals": 1,
    "assists": 0,
    "shots": 1,
    "shots_on_target": 1
  },
  {
    "id": 137131,
    "team_id": 375,
    "name": "C. R\u00f6sler",
    "position": "Defender",
    "appearances": 10,
    "minutes": 793,
    "goals": 0,
    "assists": 0,
    "shots": 1,
    "shots_on_target": 1
  },
  {
    "id": 19319,
    "team_id": 375,
    "name": "M. Olsson",
    "position": "Defender",
    "appearances": 10,
    "minutes": 1,
    "goals": 0,
    "assists": 0,
    "shots": 0,
    "shots_on_target": 0
  },
  {
    "id": 443779,
    "team_id": 375,
    "name": "N. Z\u00e4tterstr\u00f6m",
    "position": "Defender",
    "appearances": 10,
    "minutes": 630,
    "goals": 0,
    "assists": 0,
    "shots": 1,
    "shots_on_target": 0
  },
  {
    "id": 2733,
    "team_id": 375,
    "name": "J. Stryger Larsen",
    "position": "Defender",
    "appearances": 8,
    "minutes": 712,
    "goals": 0,
    "assists": 1,
    "shots": 3,
    "shots_on_target": 1
  },
  {
    "id": 129964,
    "team_id": 375,
    "name": "Busanello",
    "position": "Defender",
    "appearances": 10,
    "minutes": 900,
    "goals": 0,
    "assists": 2,
    "shots": 6,
    "shots_on_target": 1
  },
  {
    "id": 48169,
    "team_id": 375,
    "name": "O. Berg",
    "position": "Midfielder",
    "appearances": 10,
    "minutes": 368,
    "goals": 0,
    "assists": 0,
    "shots": 1,
    "shots_on_target": 0
  },
  {
    "id": 15943,
    "team_id": 375,
    "name": "S. J\u00f8rgensen",
    "position": "Midfielder",
    "appearances": 8,
    "minutes": 11,
    "goals": 0,
    "assists": 0,
    "shots": 0,
    "shots_on_target": 0
  },
  {
    "id": 394916,
    "team_id": 375,
    "name": "Z. Loukili",
    "position": "Midfielder",
    "appearances": 10,
    "minutes": 124,
    "goals": 0,
    "assists": 1,
    "shots": 0,
    "shots_on_target": 0
  },
  {
    "id": 1962,
    "team_id": 375,
    "name": "O. Lewicki",
    "position": "Midfielder",
    "appearances": 5,
    "minutes": 8,
    "goals": 0,
    "assists": 0,
    "shots": 0,
    "shots_on_target": 0
  },
  {
    "id": 39141,
    "team_id": 375,
    "name": "L. Johnsen",
    "position": "Midfielder",
    "appearances": 10,
    "minutes": 858,
    "goals": 1,
    "assists": 1,
    "shots": 8,
    "shots_on_target": 4
  },
  {
    "id": 424637,
    "team_id": 375,
    "name": "A. Skogmar",
    "position": "Midfielder",
    "appearances": 8,
    "minutes": 98,
    "goals": 0,
    "assists": 0,
    "shots": 1,
    "shots_on_target": 0
  },
  {
    "id": 335095,
    "team_id": 375,
    "name": "H. Bolin",
    "position": "Midfielder",
    "appearances": 14,
    "minutes": 979,
    "goals": 3,
    "assists": 0,
    "shots": 11,
    "shots_on_target": 4
  },
  {
    "id": 1958,
    "team_id": 375,
    "name": "A. Christiansen",
    "position": "Midfielder",
    "appearances": 12,
    "minutes": 666,
    "goals": 3,
    "assists": 1,
    "shots": 13,
    "shots_on_target": 6
  },
  {
    "id": 287374,
    "team_id": 375,
    "name": "E. Ekong",
    "position": "Midfielder",
    "appearances": 15,
    "minutes": 171,
    "goals": 0,
    "assists": 0,
    "shots": 2,
    "shots_on_target": 1
  },
  {
    "id": 306955,
    "team_id": 375,
    "name": "O. Rosengren",
    "position": "Midfielder",
    "appearances": 8,
    "minutes": 406,
    "goals": 0,
    "assists": 0,
    "shots": 0,
    "shots_on_target": 0
  },
  {
    "id": 160925,
    "team_id": 375,
    "name": "T. Ali",
    "position": "Midfielder",
    "appearances": 9,
    "minutes": 330,
    "goals": 1,
    "assists": 0,
    "shots": 6,
    "shots_on_target": 3
  },
  {
    "id": 342464,
    "team_id": 375,
    "name": "D. Gu\u00f0johnsen",
    "position": "Attacker",
    "appearances": 5,
    "minutes": 3,
    "goals": 0,
    "assists": 0,
    "shots": 0,
    "shots_on_target": 0
  },
  {
    "id": 1188,
    "team_id": 375,
    "name": "E. Botheim",
    "position": "Attacker",
    "appearances": 10,
    "minutes": 724,
    "goals": 4,
    "assists": 0,
    "shots": 18,
    "shots_on_target": 9
  }
]