[
  {
    "id": 895,
    "team_id": 45,
    "name": "J. Garner",
    "position": "Midfielder",
    "appearances": 9,
    "minutes": 816,
    "goals": 1,
    "assists": 1,
    "shots": 10,
    "shots_on_target": 4
  },
  {
    "id": 18592,
    "team_id": 45,
    "name": "I. Ndiaye",
    "position": "Attacker",
    "appearances": 9,
    "minutes": 771,
    "goals": 3,
    "assists": 1,
    "shots": 8,
    "shots_on_target": 7
  },
  {
    "id": 125743,
    "team_id": 45,
    "name": "Beto",
    "position": "Attacker",
    "appearances": 9,
    "minutes": 568,
    "goals": 1,
    "assists": 0,
    "shots": 10,
    "shots_on_target": 4
  },
  {
    "id": 195993,
    "team_id": 45,
    "name": "C. Alcaraz",
    "position": "Midfielder",
    "appearances": 7,
    "minutes": 255,
    "goals": 0,
    "assists": 0,
    "shots": 3,
    "shots_on_target": 2
  },
  {
    "id": 284500,
    "team_id": 45,
    "name": "T. Iroegbunam",
    "position": "Midfielder",
    "appearances": 6,
    "minutes": 267,
    "goals": 0,
    "assists": 0,
    "shots": 1,
    "shots_on_target": 0
  },
  {
    "id": 343684,
    "team_id": 45,
    "name": "T. Barry",
    "position": "Attacker",
    "appearances": 9,
    "minutes": 261,
    "goals": 0,
    "assists": 0,
    "shots": 3,
    "shots_on_target": 0
  },
  {
    "id": 2990,
    "team_id": 45,
    "name": "I. Gueye",
    "position": "Midfielder",
    "appearances": 9,
    "minutes": 86,
    "goals": 0,
    "assists": 0,
    "shots": 0,
    "shots_on_target": 0
  },
  {
    "id": 19187,
    "team_id": 45,
    "name": "J. Grealish",
    "position": "Midfielder",
    "appearances": 8,
    "minutes": 653,
    "goals": 1,
    "assists": 4,
    "shots": 6,
    "shots_on_target": 5
  },
  {
    "id": 148099,
    "team_id": 45,
    "name": "K. Dewsbury-Hall",
    "position": "Midfielder",
    "appearances": 8,
    "minutes": 722,
    "goals": 1,
    "assists": 1,
    "shots": 4,
    "shots_on_target": 1
  },
  {
    "id": 202854,
    "team_id": 45,
    "name": "M. R\u00f6hl",
    "position": "Midfielder",
    "appearances": 3,
    "minutes": 74,
    "goals": 0,
    "assists": 0,
    "shots": 3,
    "shots_on_target": 0
  },
  {
    "id": 304317,
    "team_id": 45,
    "name": "T. Dibling",
    "position": "Midfielder",
    "appearances": 4,
    "minutes": 74,
    "goals": 0,
    "assists": 0,
    "shots": 0,
    "shots_on_target": 0
  }
]