[
  {
    "id": 511150,
    "team_id": 25484,
    "name": "M. Duah",
    "position": "Midfielder",
    "appearances": 15,
    "minutes": 1143,
    "goals": 0,
    "assists": 0,
    "shots": 2,
    "shots_on_target": 0
  },
  {
    "id": 39365,
    "team_id": 25484,
    "name": "O. Valakari",
    "position": "Midfielder",
    "appearances": 35,
    "minutes": 2536,
    "goals": 5,
    "assists": 7,
    "shots": 28,
    "shots_on_target": 13
  },
  {
    "id": 19026,
    "team_id": 25484,
    "name": "L. de la Torre",
    "position": "Midfielder",
    "appearances": 31,
    "minutes": 2188,
    "goals": 5,
    "assists": 1,
    "shots": 19,
    "shots_on_target": 11
  },
  {
    "id": 15855,
    "team_id": 25484,
    "name": "J. Tverskov",
    "position": "Midfielder",
    "appearances": 34,
    "minutes": 3039,
    "goals": 2,
    "assists": 7,
    "shots": 11,
    "shots_on_target": 5
  },
  {
    "id": 373519,
    "team_id": 25484,
    "name": "D. Vazquez",
    "position": "Midfielder",
    "appearances": 4,
    "minutes": 176,
    "goals": 0,
    "assists": 0,
    "shots": 0,
    "shots_on_target": 0
  },
  {
    "id": 297577,
    "team_id": 25484,
    "name": "T. \u00c1ngel",
    "position": "Attacker",
    "appearances": 22,
    "minutes": 817,
    "goals": 3,
    "assists": 2,
    "shots": 6,
    "shots_on_target": 4
  },
  {
    "id": 51060,
    "team_id": 25484,
    "name": "E. Boateng",
    "position": "Midfielder",
    "appearances": 13,
    "minutes": 253,
    "goals": 0,
    "assists": 0,
    "shots": 0,
    "shots_on_target": 0
  },
  {
    "id": 2977,
    "team_id": 25484,
    "name": "A. Godoy",
    "position": "Midfielder",
    "appearances": 26,
    "minutes": 1823,
    "goals": 1,
    "assists": 1,
    "shots": 14,
    "shots_on_target": 6
  },
  {
    "id": 248,
    "team_id": 25484,
    "name": "H. Lozano",
    "position": "Attacker",
    "appearances": 27,
    "minutes": 1845,
    "goals": 9,
    "assists": 8,
    "shots": 65,
    "shots_on_target": 27
  },
  {
    "id": 129712,
    "team_id": 25484,
    "name": "A. Mighten",
    "position": "Attacker",
    "appearances": 27,
    "minutes": 1073,
    "goals": 1,
    "assists": 0,
    "shots": 11,
    "shots_on_target": 8
  },
  {
    "id": 378243,
    "team_id": 25484,
    "name": "P. Soma",
    "position": "Midfielder",
    "appearances": 6,
    "minutes": 70,
    "goals": 0,
    "assists": 0,
    "shots": 0,
    "shots_on_target": 0
  },
  {
    "id": 51204,
    "team_id": 25484,
    "name": "C. Baird",
    "position": "Attacker",
    "appearances": 6,
    "minutes": 320,
    "goals": 0,
    "assists": 0,
    "shots": 2,
    "shots_on_target": 1
  },
  {
    "id": 39347,
    "team_id": 25484,
    "name": "A. Pellegrino",
    "position": "Attacker",
    "appearances": 8,
    "minutes": 403,
    "goals": 3,
    "assists": 3,
    "shots": 10,
    "shots_on_target": 5
  },
  {
    "id": 199406,
    "team_id": 25484,
    "name": "M. Iloski",
    "position": "Attacker",
    "appearances": 14,
    "minutes": 484,
    "goals": 10,
    "assists": 1,
    "shots": 24,
    "shots_on_target": 19
  },
  {
    "id": 45017,
    "team_id": 25484,
    "name": "A. Dreyer",
    "position": "Attacker",
    "appearances": 35,
    "minutes": 3132,
    "goals": 20,
    "assists": 17,
    "shots": 84,
    "shots_on_target": 51
  },
  {
    "id": 1941,
    "team_id": 25484,
    "name": "M. Ingvartsen",
    "position": "Attacker",
    "appearances": 9,
    "minutes": 428,
    "goals": 2,
    "assists": 1,
    "shots": 13,
    "shots_on_target": 6
  },
  {
    "id": 265898,
    "team_id": 25484,
    "name": "A. Alvarado",
    "position": "Attacker",
    "appearances": 12,
    "minutes": 509,
    "goals": 0,
    "assists": 0,
    "shots": 5,
    "shots_on_target": 3
  }
]