[
  {
    "team_id": 530,
    "player_id": 753,
    "name": "Marcos Llorente",
    "position": "Midfielder",
    "appearances": 52,
    "goals": 5,
    "assists": 8,
    "shots": 35,
    "shots_on_target": 14,
    "goals_per90_simulated": 0.1,
    "assists_per90_simulated": 0.19,
    "shots_per90": 0.72,
    "sot_per90": 0.28,
    "+1_goal_pct": 10.3,
    "+1_assist_pct": 16.7,
    "soa_pct": 25.3
  },
  {
    "team_id": 530,
    "player_id": 6009,
    "name": "Julian Alvarez",
    "position": "Attacker",
    "appearances": 60,
    "goals": 30,
    "assists": 8,
    "shots": 127,
    "shots_on_target": 66,
    "goals_per90_simulated": 0.66,
    "assists_per90_simulated": 0.16,
    "shots_per90": 2.64,
    "sot_per90": 1.37,
    "+1_goal_pct": 48.2,
    "+1_assist_pct": 15.4,
    "soa_pct": 56.2
  },
  {
    "team_id": 530,
    "player_id": 6067,
    "name": "Thiago Almada",
    "position": "Midfielder",
    "appearances": 24,
    "goals": 2,
    "assists": 4,
    "shots": 37,
    "shots_on_target": 8,
    "goals_per90_simulated": 0.12,
    "assists_per90_simulated": 0.26,
    "shots_per90": 2.12,
    "sot_per90": 0.47,
    "+1_goal_pct": 11.4,
    "+1_assist_pct": 22.5,
    "soa_pct": 31.3
  },
  {
    "team_id": 530,
    "player_id": 8492,
    "name": "Alexander Sorloth",
    "position": "Attacker",
    "appearances": 56,
    "goals": 25,
    "assists": 2,
    "shots": 116,
    "shots_on_target": 57,
    "goals_per90_simulated": 0.96,
    "assists_per90_simulated": 0.07,
    "shots_per90": 4.15,
    "sot_per90": 2.07,
    "+1_goal_pct": 61.3,
    "+1_assist_pct": 7.0,
    "soa_pct": 64.0
  },
  {
    "team_id": 530,
    "player_id": 182219,
    "name": "Alejandro Baena",
    "position": "Midfielder",
    "appearances": 34,
    "goals": 7,
    "assists": 9,
    "shots": 70,
    "shots_on_target": 18,
    "goals_per90_simulated": 0.22,
    "assists_per90_simulated": 0.29,
    "shots_per90": 2.2,
    "sot_per90": 0.58,
    "+1_goal_pct": 20.6,
    "+1_assist_pct": 26.7,
    "soa_pct": 41.7
  },
  {
    "team_id": 530,
    "player_id": 323935,
    "name": "Giuliano Simeone",
    "position": "Attacker",
    "appearances": 53,
    "goals": 6,
    "assists": 9,
    "shots": 41,
    "shots_on_target": 17,
    "goals_per90_simulated": 0.16,
    "assists_per90_simulated": 0.24,
    "shots_per90": 1.09,
    "sot_per90": 0.47,
    "+1_goal_pct": 15.4,
    "+1_assist_pct": 21.3,
    "soa_pct": 33.4
  }
]