[
  {
    "team_id": 210,
    "player_id": 37163,
    "name": "D. Vente",
    "position": "Attacker",
    "appearances": 20,
    "goals": 8,
    "assists": 0,
    "shots": 25,
    "shots_on_target": 14,
    "goals_per90_simulated": 1.07,
    "assists_per90_simulated": 0.0,
    "shots_per90": 3.58,
    "sot_per90": 1.59,
    "+1_goal_pct": 65.2,
    "+1_assist_pct": 0.0,
    "soa_pct": 65.2
  },
  {
    "team_id": 210,
    "player_id": 37460,
    "name": "L. Brouwers",
    "position": "Midfielder",
    "appearances": 16,
    "goals": 2,
    "assists": 2,
    "shots": 14,
    "shots_on_target": 6,
    "goals_per90_simulated": 0.3,
    "assists_per90_simulated": 0.56,
    "shots_per90": 2.51,
    "sot_per90": 0.85,
    "+1_goal_pct": 26.0,
    "+1_assist_pct": 42.4,
    "soa_pct": 57.4
  },
  {
    "team_id": 210,
    "player_id": 174797,
    "name": "M. Rivera",
    "position": "Midfielder",
    "appearances": 7,
    "goals": 0,
    "assists": 1,
    "shots": 11,
    "shots_on_target": 6,
    "goals_per90_simulated": 0.0,
    "assists_per90_simulated": 0.56,
    "shots_per90": 4.1,
    "sot_per90": 1.75,
    "+1_goal_pct": 0.0,
    "+1_assist_pct": 41.8,
    "soa_pct": 41.8
  },
  {
    "team_id": 210,
    "player_id": 281662,
    "name": "J. Trenskow",
    "position": "Midfielder",
    "appearances": 16,
    "goals": 4,
    "assists": 2,
    "shots": 19,
    "shots_on_target": 13,
    "goals_per90_simulated": 0.65,
    "assists_per90_simulated": 0.6,
    "shots_per90": 3.63,
    "sot_per90": 1.96,
    "+1_goal_pct": 47.3,
    "+1_assist_pct": 44.4,
    "soa_pct": 70.7
  },
  {
    "team_id": 210,
    "player_id": 310037,
    "name": "M. Linday",
    "position": "Midfielder",
    "appearances": 12,
    "goals": 1,
    "assists": 1,
    "shots": 4,
    "shots_on_target": 2,
    "goals_per90_simulated": 0.18,
    "assists_per90_simulated": 0.33,
    "shots_per90": 0.9,
    "sot_per90": 0.35,
    "+1_goal_pct": 16.6,
    "+1_assist_pct": 28.3,
    "soa_pct": 40.2
  },
  {
    "team_id": 210,
    "player_id": 128311,
    "name": "R. Meerveld",
    "position": "Midfielder",
    "appearances": 21,
    "goals": 4,
    "assists": 2,
    "shots": 12,
    "shots_on_target": 10,
    "goals_per90_simulated": 0.36,
    "assists_per90_simulated": 0.32,
    "shots_per90": 1.33,
    "sot_per90": 0.9,
    "+1_goal_pct": 29.8,
    "+1_assist_pct": 27.7,
    "soa_pct": 49.3
  }
]